{
  "generator-jhipster": {
    "authenticationType": "jwt",
    "cacheProvider": "ehcache",
    "clientFramework": "angularX",
    "serverPort": "8080",
    "serviceDiscoveryType": false,
    "skipUserManagement": false,
    "withAdminUi": true,
    "baseName": "eshop",
    "buildTool": "maven",
    "databaseType": "sql",
    "devDatabaseType": "postgresql",
    "enableHibernateCache": true,
    "enableSwaggerCodegen": false,
    "enableTranslation": true,
    "jhiPrefix": "jhi",
    "languages": ["en"],
    "messageBroker": false,
    "prodDatabaseType": "postgresql",
    "searchEngine": false,
    "skipClient": false,
    "testFrameworks": [],
    "websocket": false,
    "enableGradleEnterprise": false,
    "gradleEnterpriseHost": "",
    "applicationType": "monolith",
    "packageName": "com.kabelo.eshop",
    "packageFolder": "com/kabelo/eshop",
    "jhipsterVersion": "7.3.1",
    "skipServer": false,
    "clientPackageManager": "npm",
    "dtoSuffix": "DTO",
    "entitySuffix": "",
    "reactive": false,
    "clientTheme": "none",
    "clientThemeVariant": "",
    "applicationIndex": 0,
    "entities": ["ShopUser", "Product", "ShoppingCart"],
    "skipCheckLengthOfIdentifier": false,
    "skipFakeData": false,
    "blueprints": [],
    "otherModules": [],
    "pages": [],
    "nativeLanguage": "en",
    "creationTimestamp": 1636643270645,
    "jwtSecretKey": "N2VkNjg0ZGFjMTFlMTI1NTc5ZGM1M2I2MTM1YzJiNjgxMTQzZjA2NzcyZmM1YWQzYjhiOTgxNjMyZDhmY2JmNTYzNzRhZjViOWJjYjA4NjBkMjAzYzQ1NTE5ODNhMTE5NDk5NDViMmJlYjkzZWQ0NWUxNzU0YjQ1ZjI0MDUzMGM=",
    "devServerPort": 4200,
    "lastLiquibaseTimestamp": 1636643450000
  }
}
